omniblack/logging/__init__.py
omniblack/logging/logConfig.py
omniblack.logging-0.2.1.dist-info/LICENSE.txt
omniblack.logging-0.2.1.dist-info/WHEEL
omniblack.logging-0.2.1.dist-info/METADATA
omniblack.logging-0.2.1.dist-info/RECORD
